{
  "particles": {
    "number": {
      "value": 80,
      "density": {
        "enable": true,
        "value_area": 800
      }
    },
    "color": {
      "value": "#ffffff"
    },
    "shape": {
      "type": "circle",
      "stroke": {
        "width": 0,
        "color": "#000000"
      },
      "polygon": {
        "nb_sides": 5
      },
      "image": {
        "src": "img/github.svg",
        "width": 100,
        "height": 100
      }
    },
    "opacity": {
      "value": 0.5,
      "random": false,
      "anim": {
        "enable": false,
        "speed": 1,
        "opacity_min": 0.1,
        "sync": false
      }
    },
    "size": {
      "value": 5,
      "random": true,
      "anim": {
        "enable": false,
        "speed": 40,
        "size_min": 0.1,
        "sync": false
      }
    },
    "line_linked": {
      "enable": true,
      "distance": 150,
      "color": "#ffffff",
      "opacity": 0.4,
      "width": 1
    },
    "move": {
      "enable": true,
      "speed": 6,
      "direction": "none",
      "random": false,
      "straight": false,
      "out_mode": "out",
      "attract": {
        "enable": false,
        "rotateX": 600,
        "rotateY": 1200
      }
    }
  },
  "interactivity": {
    "detect_on": "canvas",
    "events": {
      "onhover": {
        "enable": true,
        "mode": "repulse"
      },
      "onclick": {
        "enable": true,
        "mode": "push"
      },
      "resize": true
    },
    "modes": {
      "grab": {
        "distance": 400,
        "line_linked": {
          "opacity": 1
        }
      },
      "bubble": {
        "distance": 400,
        "size": 40,
        "duration": 2,
        "opacity": 8,
        "speed": 3
      },
      "repulse": {
        "distance": 200
      },
      "push": {
        "particles_nb": 4
      },
      "remove": {
        "particles_nb": 2
      }
    }
  },
  "retina_detect": true,
  "config_demo": {
    "hide_card": false,
    "background_color": "#b61924",
    "background_image": "",
    "background_position": "50% 50%",
    "background_repeat": "no-repeat",
    "background_size": "cover"
  }
}

window.onload = function () {
  
  var seconds = 00; 
  var tens = 00; 
  var appendTens = document.getElementById("tens")
  var appendSeconds = document.getElementById("seconds")
  var buttonStart = document.getElementById('button-start');
  var buttonStop = document.getElementById('button-stop');
  var buttonReset = document.getElementById('button-reset');
  var Interval ;

  buttonStart.onclick = function() {
    
     clearInterval(Interval);
     Interval = setInterval(startTimer, 10);
  }
  
    buttonStop.onclick = function() {
       clearInterval(Interval);
  }
  

  buttonReset.onclick = function() {
     clearInterval(Interval);
    tens = "00";
  	seconds = "00";
    appendTens.innerHTML = tens;
  	appendSeconds.innerHTML = seconds;
  }
  
   
  
  function startTimer () {
    tens++; 
    
    if(tens < 9){
      appendTens.innerHTML = "0" + tens;
    }
    
    if (tens > 9){
      appendTens.innerHTML = tens;
      
    } 
    
    if (tens > 99) {
      console.log("seconds");
      seconds++;
      appendSeconds.innerHTML = "0" + seconds;
      tens = 0;
      appendTens.innerHTML = "0" + 0;
    }
    
    if (seconds > 9){
      appendSeconds.innerHTML = seconds;
    }
  }
}
